firebolt_ingest/__init__.py
firebolt_ingest/aws_settings.py
firebolt_ingest/py.typed
firebolt_ingest/table_model.py
firebolt_ingest/table_service.py
firebolt_ingest/table_utils.py
firebolt_ingest/utils.py
firebolt_ingest-0.3.5.dist-info/LICENSE
firebolt_ingest-0.3.5.dist-info/METADATA
firebolt_ingest-0.3.5.dist-info/WHEEL
firebolt_ingest-0.3.5.dist-info/entry_points.txt
firebolt_ingest-0.3.5.dist-info/top_level.txt
firebolt_ingest-0.3.5.dist-info/RECORD
