Metadata-Version: 2.1
Name: firebolt-ingest
Version: 0.3.5
Summary: Firebolt ingestion library
Home-page: https://github.com/firebolt-db/firebolt-ingest
Author: Firebolt
Author-email: support@firebolt.io
License: Apache-2.0
Classifier: License :: OSI Approved :: Apache Software License
Classifier: Programming Language :: Python :: 3
Classifier: Programming Language :: Python :: 3 :: Only
Classifier: Programming Language :: Python :: 3.8
Classifier: Programming Language :: Python :: 3.9
Classifier: Programming Language :: Python :: 3.10
Classifier: Programming Language :: Python :: 3.11
Classifier: Programming Language :: Python :: 3.12
Requires-Python: >=3.8
License-File: LICENSE
Requires-Dist: firebolt-sdk >=0.9.2
Requires-Dist: pydantic <1.9.0
Requires-Dist: pyyaml
Requires-Dist: sqlparse >=0.4.2
Requires-Dist: types-PyYAML >=6.0.4
Provides-Extra: dev
Requires-Dist: mypy ; extra == 'dev'
Requires-Dist: pytest ; extra == 'dev'
Requires-Dist: pytest-cov >=3.0.0 ; extra == 'dev'
Requires-Dist: pytest-mock ; extra == 'dev'
